{
  "name": "seduce_male",
  "gender": "male",
  "moans": [
    [
      "Sound/OSF/Seduce/Male/001EFF9B.wav",
      "Sound/OSF/Seduce/Male/0033AA19.wav",
      "Sound/OSF/Seduce/Male/003E4468.wav",
      "Sound/OSF/Seduce/Male/004276E7.wav",
      "Sound/OSF/Seduce/Male/0043C799.wav",
      "Sound/OSF/Seduce/Male/00451067.wav",
      "Sound/OSF/Seduce/Male/0059C19B.wav",
      "Sound/OSF/Seduce/Male/0068E2A7.wav",
      "Sound/OSF/Seduce/Male/0077D143.wav",
      "Sound/OSF/Seduce/Male/0081DE9D.wav"
    ],
    [
      "Sound/OSF/Seduce/Male/001593E5.wav",
      "Sound/OSF/Seduce/Male/001A9CF7.wav",
      "Sound/OSF/Seduce/Male/001B8535.wav",
      "Sound/OSF/Seduce/Male/001B902E.wav",
      "Sound/OSF/Seduce/Male/001EA4B4.wav",
      "Sound/OSF/Seduce/Male/00220036.wav",
      "Sound/OSF/Seduce/Male/00244EC8.wav",
      "Sound/OSF/Seduce/Male/002648DF.wav",
      "Sound/OSF/Seduce/Male/00465BAC.wav",
      "Sound/OSF/Seduce/Male/005AC2D9.wav",
      "Sound/OSF/Seduce/Male/001EFF9B.wav",
      "Sound/OSF/Seduce/Male/0033AA19.wav",
      "Sound/OSF/Seduce/Male/0043C799.wav",
      "Sound/OSF/Seduce/Male/0059C19B.wav",
      "Sound/OSF/Seduce/Male/0077D143.wav"
    ],
    [
      "Sound/OSF/Seduce/Male/0013C1C7.wav",
      "Sound/OSF/Seduce/Male/0016A973.wav",
      "Sound/OSF/Seduce/Male/0025921C.wav",
      "Sound/OSF/Seduce/Male/002B77B8.wav",
      "Sound/OSF/Seduce/Male/002DF9D7.wav",
      "Sound/OSF/Seduce/Male/00485272.wav",
      "Sound/OSF/Seduce/Male/004B5CBC.wav",
      "Sound/OSF/Seduce/Male/004D4AB3.wav",
      "Sound/OSF/Seduce/Male/0066DD06.wav",
      "Sound/OSF/Seduce/Male/006FBCAA.wav",
      "Sound/OSF/Seduce/Male/009AB6C2.wav",
      "Sound/OSF/Seduce/Male/00CA49BB.wav",
      "Sound/OSF/Seduce/Male/00CC9D3D.wav",
      "Sound/OSF/Seduce/Male/00D634DF.wav",
      "Sound/OSF/Seduce/Male/00DA9912.wav",
      "Sound/OSF/Seduce/Male/001593E5.wav",
      "Sound/OSF/Seduce/Male/00244EC8.wav"
    ]
  ],
  "climax": [
    "Sound/OSF/Seduce/Male/0013C1C7.wav",
    "Sound/OSF/Seduce/Male/0016A973.wav",
    "Sound/OSF/Seduce/Male/0025921C.wav",
    "Sound/OSF/Seduce/Male/002B77B8.wav",
    "Sound/OSF/Seduce/Male/002DF9D7.wav",
    "Sound/OSF/Seduce/Male/00485272.wav",
    "Sound/OSF/Seduce/Male/004B5CBC.wav",
    "Sound/OSF/Seduce/Male/004D4AB3.wav",
    "Sound/OSF/Seduce/Male/0066DD06.wav",
    "Sound/OSF/Seduce/Male/006FBCAA.wav",
    "Sound/OSF/Seduce/Male/009AB6C2.wav",
    "Sound/OSF/Seduce/Male/00CA49BB.wav",
    "Sound/OSF/Seduce/Male/00CC9D3D.wav",
    "Sound/OSF/Seduce/Male/00D634DF.wav",
    "Sound/OSF/Seduce/Male/00DA9912.wav"
  ],
  "interval": {
    "base": 1.6,
    "intensityFactor": 0.8,
    "jitter": 0.5
  }
}
